zodbbrowser/__init__.py
zodbbrowser/__main__.py
zodbbrowser/browser-zope2.zcml
zodbbrowser/browser-zope3.zcml
zodbbrowser/browser.py
zodbbrowser/browser.zcml
zodbbrowser/btreesupport.py
zodbbrowser/cache.py
zodbbrowser/compat.py
zodbbrowser/configure.zcml
zodbbrowser/diff.py
zodbbrowser/history.py
zodbbrowser/interfaces.py
zodbbrowser/standalone.py
zodbbrowser/state.py
zodbbrowser/testing.py
zodbbrowser/value.py
zodbbrowser/ftests/__init__.py
zodbbrowser/ftests/browsing.txt
zodbbrowser/ftests/db-history.txt
zodbbrowser/ftests/implements-only.txt
zodbbrowser/ftests/rollback-can-be-cancelled.txt
zodbbrowser/ftests/rollbacking.txt
zodbbrowser/ftests/test_standalone.py
zodbbrowser/ftests/truncation.txt
zodbbrowser/resources/collapse.png
zodbbrowser/resources/expand.png
zodbbrowser/resources/func.js
zodbbrowser/resources/jquery-1.3.2.js
zodbbrowser/resources/zodbbrowser.css
zodbbrowser/templates/confirm_rollback.pt
zodbbrowser/templates/help.pt
zodbbrowser/templates/view_macros.pt
zodbbrowser/templates/zodbhistory.pt
zodbbrowser/templates/zodbinfo.pt
zodbbrowser/tests/__init__.py
zodbbrowser/tests/realdb.py
zodbbrowser/tests/test_browser.py
zodbbrowser/tests/test_btreesupport.py
zodbbrowser/tests/test_cache.py
zodbbrowser/tests/test_diff.py
zodbbrowser/tests/test_history.py
zodbbrowser/tests/test_standalone.py
zodbbrowser/tests/test_state.py
zodbbrowser/tests/test_value.py
zodbbrowser-0.18.0.dist-info/licenses/LICENSE
zodbbrowser-0.18.0.dist-info/METADATA
zodbbrowser-0.18.0.dist-info/WHEEL
zodbbrowser-0.18.0.dist-info/entry_points.txt
zodbbrowser-0.18.0.dist-info/top_level.txt
zodbbrowser-0.18.0.dist-info/RECORD
