Metadata-Version: 2.4
Name: zodbbrowser
Version: 0.18.0
Summary: ZODB browser
Home-page: https://github.com/mgedmin/zodbbrowser
Author: Marius Gedminas
Author-email: marius@pov.lt
Maintainer: Programmers of Vilnius
Maintainer-email: marius@pov.lt
License: ZPL 2.1
Keywords: ZODB database interactive history browser
Classifier: Development Status :: 4 - Beta
Classifier: Intended Audience :: Developers
Classifier: License :: OSI Approved :: Zope Public License
Classifier: Operating System :: OS Independent
Classifier: Programming Language :: Python :: 3.8
Classifier: Programming Language :: Python :: 3.9
Classifier: Programming Language :: Python :: 3.10
Classifier: Programming Language :: Python :: 3.11
Classifier: Programming Language :: Python :: Implementation :: CPython
Classifier: Programming Language :: Python :: Implementation :: PyPy
Requires-Python: >=3.8
License-File: LICENSE
Requires-Dist: BTrees
Requires-Dist: ZODB
Requires-Dist: ZEO
Requires-Dist: persistent
Requires-Dist: transaction
Requires-Dist: zope.app.pagetemplate
Requires-Dist: zope.app.publication
Requires-Dist: zope.component
Requires-Dist: zope.interface
Requires-Dist: zope.location
Requires-Dist: zope.publisher
Requires-Dist: zope.security
Requires-Dist: zope.traversing
Requires-Dist: zope.cachedescriptors
Requires-Dist: zope.app.authentication
Requires-Dist: zope.app.component
Requires-Dist: zope.securitypolicy
Requires-Dist: zope.app.server
Requires-Dist: zope.app.session
Requires-Dist: zope.app.zcmlfiles
Requires-Dist: zope.server
Requires-Dist: zope.error
Requires-Dist: zope.exceptions
Requires-Dist: zope.session
Requires-Dist: zope.hookable
Requires-Dist: RestrictedPython
Provides-Extra: test
Requires-Dist: mock; extra == "test"
Requires-Dist: zope.app.folder; extra == "test"
Requires-Dist: zope.app.container; extra == "test"
Requires-Dist: zope.app.testing; extra == "test"
Requires-Dist: zope.testbrowser>=5.1; extra == "test"
Requires-Dist: lxml; extra == "test"
Requires-Dist: cssselect; extra == "test"
Provides-Extra: app
Dynamic: author
Dynamic: author-email
Dynamic: classifier
Dynamic: description
Dynamic: description-content-type
Dynamic: home-page
Dynamic: keywords
Dynamic: license
Dynamic: license-file
Dynamic: maintainer
Dynamic: maintainer-email
Dynamic: provides-extra
Dynamic: requires-dist
Dynamic: requires-python
Dynamic: summary
